kids/__init__.py
kids/utils.py
kids/log_handler.py
kids-1.0.3.dist-info/METADATA
kids-1.0.3.dist-info/top_level.txt
kids-1.0.3.dist-info/metadata.json
kids-1.0.3.dist-info/DESCRIPTION.rst
kids-1.0.3.dist-info/RECORD
kids-1.0.3.dist-info/WHEEL
