Metadata-Version: 2.0
Name: kids
Version: 1.0.3
Summary: Kids Python Client
Home-page: https://github.com/fatelei/kidspy
Author: fatelei
Author-email: fatelei@gmail.com
License: BSD License
Platform: UNKNOWN
Classifier: Development Status :: 5 - Production/Stable
Classifier: Environment :: Console
Classifier: Environment :: Web Environment
Classifier: Intended Audience :: Developers
Classifier: License :: OSI Approved :: BSD License
Classifier: Programming Language :: Python :: 2.7
Classifier: Topic :: Software Development :: Libraries
Classifier: Topic :: System :: Logging
Requires-Dist: redis
